Four_bit_counter/four_bit_counter.v
module four_bit_counter (clk, clr, ld, in, out);

input ld, clr, clk;
input [3:0] in;
output [3:0] out;

reg [3:0] count;

always @(posedge clk) begin
    if (clr) begin
        count <= 4'b0000;
    end else if (ld) begin
        count <= in;
    end else begin
        count <= count + 1;
    end
end

assign out = count;

endmodule

Four_bit_counter/four_bit_counter_tb.v
`timescale 1ns/1ns
`include "four_bit_counter.v"

module four_bit_counter_tb;

reg clk, clr, ld;
reg [3:0] in;
wire [3:0] out;

four_bit_counter uut (clk, clr, ld, in, out);

initial begin 
    $dumpfile("four_bit_counter.vcd");
    $dumpvars(0, four_bit_counter_tb);

    clk = 0;
    in = 4'b1010;

    $monitor("time: %0t || clk: %0d || ld: %0b || clr: %0b || in: %04b || out: %04b", $time, clk, ld, clr, in, out);

    #3 ld = 1; clr = 0;
    #10 ld = 0;
    #10 in = 4'b1111; 
    #10 clr = 1;
    #10 clr = 0;
    #10 ld = 1;

    #30 $finish;
end

always #5 clk = ~clk;

endmodule

Four_bit_counter/four_bit_counter.vcd
$date
	Sun Jul 06 18:27:21 2025
$end
$version
	Icarus Verilog
$end
$timescale
	1ns
$end
$scope module four_bit_counter_tb $end
$var wire 4 ! out [3:0] $end
$var reg 1 " clk $end
$var reg 1 # clr $end
$var reg 4 $ in [3:0] $end
$var reg 1 % ld $end
$scope module uut $end
$var wire 1 " clk $end
$var wire 1 # clr $end
$var wire 4 & in [3:0] $end
$var wire 1 % ld $end
$var wire 4 ' out [3:0] $end
$var reg 4 ( count [3:0] $end
$upscope $end
$upscope $end
$enddefinitions $end
$comment Show the parameter values. $end
$dumpall
$end
#0
$dumpvars
bx (
bx '
b1010 &
x%
b1010 $
x#
0"
bx !
$end
#3
0#
1%
#5
b1010 !
b1010 '
b1010 (
1"
#10
0"
#13
0%
#15
b1011 !
b1011 '
b1011 (
1"
#20
0"
#23
b1111 $
b1111 &
#25
b1100 !
b1100 '
b1100 (
1"
#30
0"
#33
1#
#35
b0 !
b0 '
b0 (
1"
#40
0"
#43
0#
#45
b1 !
b1 '
b1 (
1"
#50
0"
#53
1%
#55
b1111 !
b1111 '
b1111 (
1"
