4_bit_FA/full_adder.v
module full_adder (a, b, cin, sum, cout);

// In this module I will make the full adder cicuit using the gate level modeling (structural modeling)

input a, b, cin;
output sum, cout;

wire w1, w2, w3, w4;

xor x1 (w1, a, b);
xor x2 (sum, w1, cin);
and x3 (w2, a, b);
and x4 (w3, b, cin);
and x5 (w4, cin, a);
or x6 (cout, w2, w3, w4);

endmodule

4_bit_FA/full_adder_tb.v
`timescale 1ns/1ns
`include "full_adder.v"

module full_adder_tb;

reg a, b, cin;
wire sum, cout;
integer i;

full_adder uut (a, b, cin, sum, cout);

initial begin

    $dumpfile("full_adder.vcd");
    $dumpvars(0, full_adder_tb);

    $monitor("a: %0b || b: %0b || cin: %0b || sum: %0b || cout: %0b", a, b, cin, sum, cout);

    for (i = 0; i < 8; i = i + 1) begin
        {a, b, cin} = i;
        #5;
    end

    #10 $finish;
end

endmodule

4_bit_FA/full_adder.vcd
$date
	Mon Aug 18 19:54:41 2025
$end
$version
	Icarus Verilog
$end
$timescale
	1ns
$end
$scope module full_adder_tb $end
$var wire 1 ! sum $end
$var wire 1 " cout $end
$var reg 1 # a $end
$var reg 1 $ b $end
$var reg 1 % cin $end
$var integer 32 & i [31:0] $end
$scope module uut $end
$var wire 1 # a $end
$var wire 1 $ b $end
$var wire 1 % cin $end
$var wire 1 " cout $end
$var wire 1 ! sum $end
$var wire 1 ' w1 $end
$var wire 1 ( w2 $end
$var wire 1 ) w3 $end
$var wire 1 * w4 $end
$upscope $end
$upscope $end
$enddefinitions $end
$comment Show the parameter values. $end
$dumpall
$end
#0
$dumpvars
0*
0)
0(
0'
b0 &
0%
0$
0#
0"
0!
$end
#5
1!
1%
b1 &
#10
1'
1!
1$
0%
b10 &
#15
1"
0!
1)
1%
b11 &
#20
0"
1!
0)
1#
0$
0%
b100 &
#25
1"
0!
1*
1%
b101 &
#30
0'
1(
0!
0*
1$
0%
b110 &
#35
1!
1)
1*
1%
b111 &
#40
b1000 &
