Rising_edge_detector/risingedgedetector.v
module risingedgedetector (clk, d, rst, out);
  
    reg q;
    input clk;
    input d; 
    input rst;
    output reg out;

    always @(posedge clk or posedge rst) begin
        if (rst) begin
            q   <= 1'b0;
            out <= 1'b0;
        end else begin
            out <= d & ~q;  
            q   <= d;       
        end
    end
  
endmodule

Rising_edge_detector/risingedgedetector_tb.v
`timescale 1ns/1ns
`include "risingedgedetector.v"

module risingedgedetector_tb;

reg clk, rst, d;
wire out;

risingedgedetector uut (clk, d, rst, out);

always #5 clk = ~clk;

initial begin
    $dumpfile("risingedgedetector.vcd");
    $dumpvars(0, risingedgedetector_tb);

    clk = 0;
    rst = 1; 
    d = 0;

    $monitor ("Time: %0t || clk: %0d || rst: %0b || d: %0b || out: %0b", $time, clk, rst, d, out);

    #8 rst = 0;
    #3 d = 1;
    #10 d = 0;
    #10 d = 0;
    #10 d = 1;

    #10 $finish;

end
endmodule

Rising_edge_detector/risingedgedetector.vcd
$date
	Sat Jul 05 17:03:28 2025
$end
$version
	Icarus Verilog
$end
$timescale
	1ns
$end
$scope module risingedgedetector_tb $end
$var wire 1 ! out $end
$var reg 1 " clk $end
$var reg 1 # d $end
$var reg 1 $ rst $end
$scope module uut $end
$var wire 1 " clk $end
$var wire 1 # d $end
$var wire 1 $ rst $end
$var reg 1 ! out $end
$var reg 1 % q $end
$upscope $end
$upscope $end
$enddefinitions $end
$comment Show the parameter values. $end
$dumpall
$end
#0
$dumpvars
0%
1$
0#
0"
0!
$end
#5
1"
#8
0$
#10
0"
#11
1#
#15
1%
1!
1"
#20
0"
#21
0#
#25
0%
0!
1"
#30
0"
#35
1"
#40
0"
#41
1#
#45
1%
1!
1"
