D_ff/d_ff.v
module d_ff (q, clk, d, rst);

    output reg q;
    input clk;
    input d;
    input rst;

    always @(posedge clk or posedge rst) begin
        if (rst)
            q <= 1'b0;       
        else
            q <= d;         
    end
endmodule

D_ff/d_ff_tb.v
`timescale 1ns/1ns
`include "d_ff.v"

module d_ff_tb;

    reg clk, d, rst;
    wire q;

    d_ff uut (.q(q), .clk(clk), .d(d), .rst(rst));

    always #5 clk = ~clk;

    initial begin
        $dumpfile("d_ff.vcd");
        $dumpvars(0, d_ff_tb);

        $monitor("time: %4t || clk: %b || d: %b || rst: %b || q: %b", $time, clk, d, rst, q);

        clk = 0;
        rst = 1;  
        d = 0;

        #8  rst = 0;  
        #5  d = 1;    
        #10 d = 0;    
        #10 d = 1;   
        #10 d = 0;    

        #10 $finish;
    end

endmodule

D_ff/d_ff.vcd
$date
	Fri Jul 04 14:47:46 2025
$end
$version
	Icarus Verilog
$end
$timescale
	1ns
$end
$scope module d_ff_tb $end
$var wire 1 ! q $end
$var reg 1 " clk $end
$var reg 1 # d $end
$var reg 1 $ rst $end
$scope module uut $end
$var wire 1 " clk $end
$var wire 1 # d $end
$var wire 1 $ rst $end
$var reg 1 ! q $end
$upscope $end
$upscope $end
$enddefinitions $end
$comment Show the parameter values. $end
$dumpall
$end
#0
$dumpvars
1$
0#
0"
0!
$end
#5
1"
#8
0$
#10
0"
#13
1#
#15
1!
1"
#20
0"
#23
0#
#25
0!
1"
#30
0"
#33
1#
#35
1!
1"
#40
0"
#43
0#
#45
0!
1"
