Shift_registers/SISO/siso.v
module siso (clk, rst, sin, sout);

input clk, rst, sin;
output sout; 

reg [3:0] shift_reg;

always@ (posedge clk or posedge rst) begin
    if (rst) begin
        shift_reg <= 4'b0000;
    end else begin
        shift_reg <= {shift_reg[2:0], sin};      
    end
end

assign sout = shift_reg[3];

endmodule

Shift_registers/SISO/siso_tb.v
`timescale 1ns/1ns
`include "siso.v"

module siso_tb;

reg clk, rst, sin;
wire sout;

siso uut (clk, rst, sin, sout);

initial begin
    $dumpfile("siso.vcd");
    $dumpvars(0, siso_tb);

    $monitor("Time: %0t || clk: %b || rst: %b || sin: %b || sout: %b", $time, clk, rst, sin, sout);

    clk = 0;
    rst = 1;
    sin = 0;
    #10 rst = 0; 

        sin = 1; #10;
        sin = 0; #10;
        sin = 1; #10;
        sin = 1; #10;

        #50 $finish;
end

always #5 clk = ~clk;

endmodule

Shift_registers/SISO/siso.vcd
$date
	Mon Aug 25 17:32:03 2025
$end
$version
	Icarus Verilog
$end
$timescale
	1ns
$end
$scope module siso_tb $end
$var wire 1 ! sout $end
$var reg 1 " clk $end
$var reg 1 # rst $end
$var reg 1 $ sin $end
$scope module uut $end
$var wire 1 " clk $end
$var wire 1 # rst $end
$var wire 1 $ sin $end
$var wire 1 ! sout $end
$var reg 4 % shift_reg [3:0] $end
$upscope $end
$upscope $end
$enddefinitions $end
$comment Show the parameter values. $end
$dumpall
$end
#0
$dumpvars
b0 %
0$
1#
0"
0!
$end
#5
1"
#10
0"
1$
0#
#15
b1 %
1"
#20
0"
0$
#25
b10 %
1"
#30
0"
1$
#35
b101 %
1"
#40
0"
#45
1!
b1011 %
1"
#50
0"
#55
0!
b111 %
1"
#60
0"
#65
1!
b1111 %
1"
