Music_playing_machine/music_player.v
// NOTE: This module is having with correct logic, but is not able to generate the SCHEMATIC DESIGN in Xilinx vivado software, I am working on the issue...

module music_player (clk, rst, play_pause, next, prev, is_playing, song);

input clk, rst, play_pause, next, prev;
output reg is_playing;
output reg [1:0] song;

// play_pause: Play/Pause toggle button
// next: Next song button
// prev: Previous song button
// is_playing: Output high when playing, low when paused
// song: Current song number (0 to 3)
 
parameter IDLE = 2'b00, PLAYING = 2'b01, PAUSE = 2'b10, NEXT = 2'b00;
reg [1:0] state, next_state;

always @(posedge clk or posedge rst) begin
    if (rst) begin
        is_playing <= 1'b0;
        song <= 2'b00;
        state <= IDLE;
    end else begin
        state <= next_state;
    end

    if (play_pause) begin
        is_playing <= ~is_playing;
    end

    if (is_playing) begin
        if (next && !prev) begin
            song <= (song == 2'd3) ? 0: song + 1;        
        end else if (!next && prev) begin
            song <= (song == 2'd0) ? 3: song - 1; 
        end
    end
end

always @(*) begin
    case (state)
    IDLE: begin
        next_state = (is_playing == 1'b1) ? PLAYING:IDLE;
    end 
    PLAYING: begin
        next_state = (is_playing == 1'b1) ? PLAYING:PAUSE;
    end
    PAUSE: begin
        next_state = (is_playing == 1'b1) ? PLAYING:PAUSE;
    end
    endcase
end
endmodule

Music_playing_machine/music_player_tb.v
`timescale 1ns/1ns
`include "music_player.v"

module music_player_tb;

reg clk, rst, play_pause, next, prev;
wire is_playing;
wire [1:0] song;

music_player uut (clk, rst, play_pause, next, prev, is_playing, song);

initial begin
    $dumpfile("music_player.vcd");
    $dumpvars(0, music_player_tb);

    $monitor("Time: %0t || play_pause: %0b || next: %0b || prev: %0b || is_playing: %0b || song: %0d", $time, play_pause, next, prev, is_playing, song);

    clk = 0;
    rst = 1;
    play_pause = 0;
    next = 0;
    prev = 0;

    #5 rst = 0;  

    // Test Vector 1: 
    #5  play_pause = 1; next = 0; prev = 0; 
    #10 play_pause = 0;                      

    // Test Vector 2: 
    #10 play_pause = 0; next = 1; prev = 0;  
    #10 next = 0;                            

    // Test Vector 3:
    #10 play_pause = 0; next = 1; prev = 0;  
    #10 next = 0;                            
    // Test Vector 4: 
    #10 play_pause = 0; next = 0; prev = 1;  
    #10 prev = 0;        

    // Test vector 5:
    #10 play_pause = 1; next = 0; prev = 0;  
    #10 play_pause = 0;                      

    #10 $finish;
end

always #5 clk = ~clk;

endmodule

Music_playing_machine/music_player.vcd
$date
	Thu Jul 24 19:26:24 2025
$end
$version
	Icarus Verilog
$end
$timescale
	1ns
$end
$scope module music_player_tb $end
$var wire 2 ! song [1:0] $end
$var wire 1 " is_playing $end
$var reg 1 # clk $end
$var reg 1 $ next $end
$var reg 1 % play_pause $end
$var reg 1 & prev $end
$var reg 1 ' rst $end
$scope module uut $end
$var wire 1 # clk $end
$var wire 1 $ next $end
$var wire 1 % play_pause $end
$var wire 1 & prev $end
$var wire 1 ' rst $end
$var parameter 2 ( IDLE $end
$var parameter 2 ) NEXT $end
$var parameter 2 * PAUSE $end
$var parameter 2 + PLAYING $end
$var reg 1 " is_playing $end
$var reg 2 , next_state [1:0] $end
$var reg 2 - song [1:0] $end
$var reg 2 . state [1:0] $end
$upscope $end
$upscope $end
$enddefinitions $end
$comment Show the parameter values. $end
$dumpall
b1 +
b10 *
b0 )
b0 (
$end
#0
$dumpvars
b0 .
b0 -
b0 ,
1'
0&
0%
0$
0#
0"
b0 !
$end
#5
1#
0'
#10
0#
1%
#15
b1 ,
1"
1#
#20
0#
0%
#25
b1 .
1#
#30
0#
1$
#35
b1 !
b1 -
1#
#40
0#
0$
#45
1#
#50
0#
1$
#55
b10 !
b10 -
1#
#60
0#
0$
#65
1#
#70
0#
1&
#75
b1 !
b1 -
1#
#80
0#
0&
#85
1#
#90
0#
1%
#95
b10 ,
0"
1#
#100
0#
0%
#105
b10 .
1#
