Digital_lock/digital_lock.v
// The below written is the code for a digital lock which will open when the correct sequence 
// "1101" is entered

module digital_lock (clk, rst, in_seq, out);

input clk, rst;
input in_seq;
output reg out;

reg [2:0] state, next_state;
parameter S0 = 3'b000, S1 = 3'b001, S2 = 3'b010, S3 = 3'b011, OPEN_STATE = 3'b100;

always @(posedge clk or posedge rst) begin
    if (rst) begin
        state <= S0;
    end else begin
        state <= next_state;
    end
end

always @(*) begin
    out = 0;
    case (state)
    S0: next_state <= (in_seq == 1'b1) ? S1:S0;
    S1: next_state <= (in_seq == 1'b1) ? S2:S0;
    S2: next_state <= (in_seq == 1'b0) ? S3:S0;
    S3: next_state <= (in_seq == 1'b1) ? OPEN_STATE:S0;
    OPEN_STATE: begin
        out <= 1;
        next_state <= S0;  
    end
        default: begin
            next_state <= S0;
        end
    endcase
end
    
endmodule

Digital_lock/digital_lock_tb.v
`timescale 1ns/1ps
`include "digital_lock.v"

module digital_lock_tb;

reg clk, rst;
reg in_seq;
wire out;

digital_lock uut (clk, rst, in_seq, out);

initial begin

    $dumpfile("digital_lock.vcd");
    $dumpvars(0, digital_lock_tb);

    $monitor("Time: %t || clk: %b || rst: %b || in_seq: %b || out = %b", $time, clk, rst, in_seq, out);

    clk = 0; rst = 1; in_seq = 1'b0; 

    #5 rst = 0;

    #10 in_seq = 1'b1;
    #10 in_seq = 1'b1;
    #10 in_seq = 1'b0;
    #10 in_seq = 1'b1;
    
    #20 $finish;
end

always #5 clk = ~clk; 

endmodule

Digital_lock/digital_lock.vcd
$date
	Sun Sep 07 19:13:15 2025
$end
$version
	Icarus Verilog
$end
$timescale
	1ps
$end
$scope module digital_lock_tb $end
$var wire 1 ! out $end
$var reg 1 " clk $end
$var reg 1 # in_seq $end
$var reg 1 $ rst $end
$scope module uut $end
$var wire 1 " clk $end
$var wire 1 # in_seq $end
$var wire 1 $ rst $end
$var parameter 3 % OPEN_STATE $end
$var parameter 3 & S0 $end
$var parameter 3 ' S1 $end
$var parameter 3 ( S2 $end
$var parameter 3 ) S3 $end
$var reg 3 * next_state [2:0] $end
$var reg 1 ! out $end
$var reg 3 + state [2:0] $end
$upscope $end
$upscope $end
$enddefinitions $end
$comment Show the parameter values. $end
$dumpall
b11 )
b10 (
b1 '
b0 &
b100 %
$end
#0
$dumpvars
b0 +
b0 *
1$
0#
0"
0!
$end
#5000
1"
0$
#10000
0"
#15000
b1 *
1"
1#
#20000
0"
#25000
b10 *
b1 +
1"
#30000
0"
#35000
b10 +
b11 *
1"
0#
#40000
0"
#45000
b11 +
b100 *
1"
1#
#50000
0"
#55000
b0 *
1!
b100 +
1"
#60000
0"
#65000
b1 *
0!
b0 +
1"
