PWM_pulse_generator/pwm.v
module pwm (clk, rst, duty_cycle, pwm_out);

input clk, rst;
input [7:0] duty_cycle;
output pwm_out;

reg [7:0] counter;

always @(posedge clk or posedge rst) begin
    if (rst) begin
        counter <= 8'b0000_0000;
    end else begin
        counter <= counter + 1;  
    end
end

assign pwm_out = (counter < duty_cycle) ? 1'b1:1'b0;
    
endmodule

PWM_pulse_generator/pwm_tb.v
`timescale 1ns/1ns
`include "pwm.v"

module pwm_tb;

reg clk, rst;
reg [7:0] duty_cycle;
wire pwm_out;

pwm uut (clk, rst, duty_cycle, pwm_out);

initial begin 

    $dumpfile("pwm.vcd");
    $dumpvars(0, pwm_tb);

    $monitor("Time: %0t || clk: %b || rst: %b || duty_cycle: %d || pwm_out: %b", $time, clk, rst, duty_cycle, pwm_out);

    clk = 1'b0;
    duty_cycle = 0;
    rst = 1'b1;

    #5 rst = 1'b0;

    #5 duty_cycle = 60;
    #10 duty_cycle = 60;
    #10 duty_cycle = 60;
    #10 duty_cycle = 60;
    #10 duty_cycle = 60;
    #10 duty_cycle = 60;

    #3000 $finish;
end

always #5 clk = ~clk;

endmodule

PWM_pulse_generator/pwm.vcd
$date
	Thu Aug 28 13:15:10 2025
$end
$version
	Icarus Verilog
$end
$timescale
	1ns
$end
$scope module pwm_tb $end
$var wire 1 ! pwm_out $end
$var reg 1 " clk $end
$var reg 8 # duty_cycle [7:0] $end
$var reg 1 $ rst $end
$scope module uut $end
$var wire 1 " clk $end
$var wire 8 % duty_cycle [7:0] $end
$var wire 1 $ rst $end
$var wire 1 ! pwm_out $end
$var reg 8 & counter [7:0] $end
$upscope $end
$upscope $end
$enddefinitions $end
$comment Show the parameter values. $end
$dumpall
$end
#0
$dumpvars
b0 &
b0 %
1$
b0 #
0"
0!
$end
#5
b1 &
1"
0$
#10
1!
0"
b111100 #
b111100 %
#15
b10 &
1"
#20
0"
#25
b11 &
1"
#30
0"
#35
b100 &
1"
#40
0"
#45
b101 &
1"
#50
0"
#55
b110 &
1"
#60
0"
#65
b111 &
1"
#70
0"
#75
b1000 &
1"
#80
0"
#85
b1001 &
1"
#90
0"
#95
b1010 &
1"
#100
0"
#105
b1011 &
1"
#110
0"
#115
b1100 &
1"
#120
0"
#125
b1101 &
1"
#130
0"
#135
b1110 &
1"
#140
0"
#145
b1111 &
1"
#150
0"
#155
b10000 &
1"
#160
0"
#165
b10001 &
1"
#170
0"
#175
b10010 &
1"
#180
0"
#185
b10011 &
1"
#190
0"
#195
b10100 &
1"
#200
0"
#205
b10101 &
1"
#210
0"
#215
b10110 &
1"
#220
0"
#225
b10111 &
1"
#230
0"
#235
b11000 &
1"
#240
0"
#245
b11001 &
1"
#250
0"
#255
b11010 &
1"
#260
0"
#265
b11011 &
1"
#270
0"
#275
b11100 &
1"
#280
0"
#285
b11101 &
1"
#290
0"
#295
b11110 &
1"
#300
0"
#305
b11111 &
1"
#310
0"
#315
b100000 &
1"
#320
0"
#325
b100001 &
1"
#330
0"
#335
b100010 &
1"
#340
0"
#345
b100011 &
1"
#350
0"
#355
b100100 &
1"
#360
0"
#365
b100101 &
1"
#370
0"
#375
b100110 &
1"
#380
0"
#385
b100111 &
1"
#390
0"
#395
b101000 &
1"
#400
0"
#405
b101001 &
1"
#410
0"
#415
b101010 &
1"
#420
0"
#425
b101011 &
1"
#430
0"
#435
b101100 &
1"
#440
0"
#445
b101101 &
1"
#450
0"
#455
b101110 &
1"
#460
0"
#465
b101111 &
1"
#470
0"
#475
b110000 &
1"
#480
0"
#485
b110001 &
1"
#490
0"
#495
b110010 &
1"
#500
0"
#505
b110011 &
1"
#510
0"
#515
b110100 &
1"
#520
0"
#525
b110101 &
1"
#530
0"
#535
b110110 &
1"
#540
0"
#545
b110111 &
1"
#550
0"
#555
b111000 &
1"
#560
0"
#565
b111001 &
1"
#570
0"
#575
b111010 &
1"
#580
0"
#585
b111011 &
1"
#590
0"
#595
0!
b111100 &
1"
#600
0"
#605
b111101 &
1"
#610
0"
#615
b111110 &
1"
#620
0"
#625
b111111 &
1"
#630
0"
#635
b1000000 &
1"
#640
0"
#645
b1000001 &
1"
#650
0"
#655
b1000010 &
1"
#660
0"
#665
b1000011 &
1"
#670
0"
#675
b1000100 &
1"
#680
0"
#685
b1000101 &
1"
#690
0"
#695
b1000110 &
1"
#700
0"
#705
b1000111 &
1"
#710
0"
#715
b1001000 &
1"
#720
0"
#725
b1001001 &
1"
#730
0"
#735
b1001010 &
1"
#740
0"
#745
b1001011 &
1"
#750
0"
#755
b1001100 &
1"
#760
0"
#765
b1001101 &
1"
#770
0"
#775
b1001110 &
1"
#780
0"
#785
b1001111 &
1"
#790
0"
#795
b1010000 &
1"
#800
0"
#805
b1010001 &
1"
#810
0"
#815
b1010010 &
1"
#820
0"
#825
b1010011 &
1"
#830
0"
#835
b1010100 &
1"
#840
0"
#845
b1010101 &
1"
#850
0"
#855
b1010110 &
1"
#860
0"
#865
b1010111 &
1"
#870
0"
#875
b1011000 &
1"
#880
0"
#885
b1011001 &
1"
#890
0"
#895
b1011010 &
1"
#900
0"
#905
b1011011 &
1"
#910
0"
#915
b1011100 &
1"
#920
0"
#925
b1011101 &
1"
#930
0"
#935
b1011110 &
1"
#940
0"
#945
b1011111 &
1"
#950
0"
#955
b1100000 &
1"
#960
0"
#965
b1100001 &
1"
#970
0"
#975
b1100010 &
1"
#980
0"
#985
b1100011 &
1"
#990
0"
#995
b1100100 &
1"
#1000
0"
#1005
b1100101 &
1"
#1010
0"
#1015
b1100110 &
1"
#1020
0"
#1025
b1100111 &
1"
#1030
0"
#1035
b1101000 &
1"
#1040
0"
#1045
b1101001 &
1"
#1050
0"
#1055
b1101010 &
1"
#1060
0"
#1065
b1101011 &
1"
#1070
0"
#1075
b1101100 &
1"
#1080
0"
#1085
b1101101 &
1"
#1090
0"
#1095
b1101110 &
1"
#1100
0"
#1105
b1101111 &
1"
#1110
0"
#1115
b1110000 &
1"
#1120
0"
#1125
b1110001 &
1"
#1130
0"
#1135
b1110010 &
1"
#1140
0"
#1145
b1110011 &
1"
#1150
0"
#1155
b1110100 &
1"
#1160
0"
#1165
b1110101 &
1"
#1170
0"
#1175
b1110110 &
1"
#1180
0"
#1185
b1110111 &
1"
#1190
0"
#1195
b1111000 &
1"
#1200
0"
#1205
b1111001 &
1"
#1210
0"
#1215
b1111010 &
1"
#1220
0"
#1225
b1111011 &
1"
#1230
0"
#1235
b1111100 &
1"
#1240
0"
#1245
b1111101 &
1"
#1250
0"
#1255
b1111110 &
1"
#1260
0"
#1265
b1111111 &
1"
#1270
0"
#1275
b10000000 &
1"
#1280
0"
#1285
b10000001 &
1"
#1290
0"
#1295
b10000010 &
1"
#1300
0"
#1305
b10000011 &
1"
#1310
0"
#1315
b10000100 &
1"
#1320
0"
#1325
b10000101 &
1"
#1330
0"
#1335
b10000110 &
1"
#1340
0"
#1345
b10000111 &
1"
#1350
0"
#1355
b10001000 &
1"
#1360
0"
#1365
b10001001 &
1"
#1370
0"
#1375
b10001010 &
1"
#1380
0"
#1385
b10001011 &
1"
#1390
0"
#1395
b10001100 &
1"
#1400
0"
#1405
b10001101 &
1"
#1410
0"
#1415
b10001110 &
1"
#1420
0"
#1425
b10001111 &
1"
#1430
0"
#1435
b10010000 &
1"
#1440
0"
#1445
b10010001 &
1"
#1450
0"
#1455
b10010010 &
1"
#1460
0"
#1465
b10010011 &
1"
#1470
0"
#1475
b10010100 &
1"
#1480
0"
#1485
b10010101 &
1"
#1490
0"
#1495
b10010110 &
1"
#1500
0"
#1505
b10010111 &
1"
#1510
0"
#1515
b10011000 &
1"
#1520
0"
#1525
b10011001 &
1"
#1530
0"
#1535
b10011010 &
1"
#1540
0"
#1545
b10011011 &
1"
#1550
0"
#1555
b10011100 &
1"
#1560
0"
#1565
b10011101 &
1"
#1570
0"
#1575
b10011110 &
1"
#1580
0"
#1585
b10011111 &
1"
#1590
0"
#1595
b10100000 &
1"
#1600
0"
#1605
b10100001 &
1"
#1610
0"
#1615
b10100010 &
1"
#1620
0"
#1625
b10100011 &
1"
#1630
0"
#1635
b10100100 &
1"
#1640
0"
#1645
b10100101 &
1"
#1650
0"
#1655
b10100110 &
1"
#1660
0"
#1665
b10100111 &
1"
#1670
0"
#1675
b10101000 &
1"
#1680
0"
#1685
b10101001 &
1"
#1690
0"
#1695
b10101010 &
1"
#1700
0"
#1705
b10101011 &
1"
#1710
0"
#1715
b10101100 &
1"
#1720
0"
#1725
b10101101 &
1"
#1730
0"
#1735
b10101110 &
1"
#1740
0"
#1745
b10101111 &
1"
#1750
0"
#1755
b10110000 &
1"
#1760
0"
#1765
b10110001 &
1"
#1770
0"
#1775
b10110010 &
1"
#1780
0"
#1785
b10110011 &
1"
#1790
0"
#1795
b10110100 &
1"
#1800
0"
#1805
b10110101 &
1"
#1810
0"
#1815
b10110110 &
1"
#1820
0"
#1825
b10110111 &
1"
#1830
0"
#1835
b10111000 &
1"
#1840
0"
#1845
b10111001 &
1"
#1850
0"
#1855
b10111010 &
1"
#1860
0"
#1865
b10111011 &
1"
#1870
0"
#1875
b10111100 &
1"
#1880
0"
#1885
b10111101 &
1"
#1890
0"
#1895
b10111110 &
1"
#1900
0"
#1905
b10111111 &
1"
#1910
0"
#1915
b11000000 &
1"
#1920
0"
#1925
b11000001 &
1"
#1930
0"
#1935
b11000010 &
1"
#1940
0"
#1945
b11000011 &
1"
#1950
0"
#1955
b11000100 &
1"
#1960
0"
#1965
b11000101 &
1"
#1970
0"
#1975
b11000110 &
1"
#1980
0"
#1985
b11000111 &
1"
#1990
0"
#1995
b11001000 &
1"
#2000
0"
#2005
b11001001 &
1"
#2010
0"
#2015
b11001010 &
1"
#2020
0"
#2025
b11001011 &
1"
#2030
0"
#2035
b11001100 &
1"
#2040
0"
#2045
b11001101 &
1"
#2050
0"
#2055
b11001110 &
1"
#2060
0"
#2065
b11001111 &
1"
#2070
0"
#2075
b11010000 &
1"
#2080
0"
#2085
b11010001 &
1"
#2090
0"
#2095
b11010010 &
1"
#2100
0"
#2105
b11010011 &
1"
#2110
0"
#2115
b11010100 &
1"
#2120
0"
#2125
b11010101 &
1"
#2130
0"
#2135
b11010110 &
1"
#2140
0"
#2145
b11010111 &
1"
#2150
0"
#2155
b11011000 &
1"
#2160
0"
#2165
b11011001 &
1"
#2170
0"
#2175
b11011010 &
1"
#2180
0"
#2185
b11011011 &
1"
#2190
0"
#2195
b11011100 &
1"
#2200
0"
#2205
b11011101 &
1"
#2210
0"
#2215
b11011110 &
1"
#2220
0"
#2225
b11011111 &
1"
#2230
0"
#2235
b11100000 &
1"
#2240
0"
#2245
b11100001 &
1"
#2250
0"
#2255
b11100010 &
1"
#2260
0"
#2265
b11100011 &
1"
#2270
0"
#2275
b11100100 &
1"
#2280
0"
#2285
b11100101 &
1"
#2290
0"
#2295
b11100110 &
1"
#2300
0"
#2305
b11100111 &
1"
#2310
0"
#2315
b11101000 &
1"
#2320
0"
#2325
b11101001 &
1"
#2330
0"
#2335
b11101010 &
1"
#2340
0"
#2345
b11101011 &
1"
#2350
0"
#2355
b11101100 &
1"
#2360
0"
#2365
b11101101 &
1"
#2370
0"
#2375
b11101110 &
1"
#2380
0"
#2385
b11101111 &
1"
#2390
0"
#2395
b11110000 &
1"
#2400
0"
#2405
b11110001 &
1"
#2410
0"
#2415
b11110010 &
1"
#2420
0"
#2425
b11110011 &
1"
#2430
0"
#2435
b11110100 &
1"
#2440
0"
#2445
b11110101 &
1"
#2450
0"
#2455
b11110110 &
1"
#2460
0"
#2465
b11110111 &
1"
#2470
0"
#2475
b11111000 &
1"
#2480
0"
#2485
b11111001 &
1"
#2490
0"
#2495
b11111010 &
1"
#2500
0"
#2505
b11111011 &
1"
#2510
0"
#2515
b11111100 &
1"
#2520
0"
#2525
b11111101 &
1"
#2530
0"
#2535
b11111110 &
1"
#2540
0"
#2545
b11111111 &
1"
#2550
0"
#2555
1!
b0 &
1"
#2560
0"
#2565
b1 &
1"
#2570
0"
#2575
b10 &
1"
#2580
0"
#2585
b11 &
1"
#2590
0"
#2595
b100 &
1"
#2600
0"
#2605
b101 &
1"
#2610
0"
#2615
b110 &
1"
#2620
0"
#2625
b111 &
1"
#2630
0"
#2635
b1000 &
1"
#2640
0"
#2645
b1001 &
1"
#2650
0"
#2655
b1010 &
1"
#2660
0"
#2665
b1011 &
1"
#2670
0"
#2675
b1100 &
1"
#2680
0"
#2685
b1101 &
1"
#2690
0"
#2695
b1110 &
1"
#2700
0"
#2705
b1111 &
1"
#2710
0"
#2715
b10000 &
1"
#2720
0"
#2725
b10001 &
1"
#2730
0"
#2735
b10010 &
1"
#2740
0"
#2745
b10011 &
1"
#2750
0"
#2755
b10100 &
1"
#2760
0"
#2765
b10101 &
1"
#2770
0"
#2775
b10110 &
1"
#2780
0"
#2785
b10111 &
1"
#2790
0"
#2795
b11000 &
1"
#2800
0"
#2805
b11001 &
1"
#2810
0"
#2815
b11010 &
1"
#2820
0"
#2825
b11011 &
1"
#2830
0"
#2835
b11100 &
1"
#2840
0"
#2845
b11101 &
1"
#2850
0"
#2855
b11110 &
1"
#2860
0"
#2865
b11111 &
1"
#2870
0"
#2875
b100000 &
1"
#2880
0"
#2885
b100001 &
1"
#2890
0"
#2895
b100010 &
1"
#2900
0"
#2905
b100011 &
1"
#2910
0"
#2915
b100100 &
1"
#2920
0"
#2925
b100101 &
1"
#2930
0"
#2935
b100110 &
1"
#2940
0"
#2945
b100111 &
1"
#2950
0"
#2955
b101000 &
1"
#2960
0"
#2965
b101001 &
1"
#2970
0"
#2975
b101010 &
1"
#2980
0"
#2985
b101011 &
1"
#2990
0"
#2995
b101100 &
1"
#3000
0"
#3005
b101101 &
1"
#3010
0"
#3015
b101110 &
1"
#3020
0"
#3025
b101111 &
1"
#3030
0"
#3035
b110000 &
1"
#3040
0"
#3045
b110001 &
1"
#3050
0"
#3055
b110010 &
1"
