Priority_encoder/priority_encoder_new.v
module priority_encoder_new (d, out, valid);
    
input valid;
input [7:0] d;
output reg [2:0] out;
integer i;

always @(*) begin
    if(valid) begin
        for(i = 0; i < 8; i = i + 1) begin
            if(d[i] == 1'b1) begin
                out = i;
            end
        end
    end
end

endmodule

Priority_encoder/priority_encoder_new_tb.v
`timescale 1ns/1ns
`include "priority_encoder_new.v"

module priority_encoder_new_tb;

reg valid;
reg [7:0] d;
wire [2:0] out;

priority_encoder_new uut (d, out, valid);

initial begin

    $dumpfile("priority_encoder_new.vcd");
    $dumpvars(0, priority_encoder_tb);

    $monitor("valid: %0b || d: %08b || out: %03b", valid, d, out);

    valid = 1'b0;
    d = 8'b0000_0000;
    
    #3 valid = 1'b1; d = 8'b0000_0001;
    #3 valid = 1'b1; d = 8'b0000_0010;
    #3 valid = 1'b1; d = 8'b0000_0100;
    #3 valid = 1'b1; d = 8'b0000_1000;
    #3 valid = 1'b1; d = 8'b0001_0000;
    #3 valid = 1'b1; d = 8'b0010_0000;
    #3 valid = 1'b1; d = 8'b0100_0000;
    #3 valid = 1'b1; d = 8'b1000_0000;

    #10 $finish;
end

endmodule

Priority_encoder/priority_encoder_new.vcd
$date
	Fri Aug 15 03:15:00 2025
$end
$version
	Icarus Verilog
$end
$timescale
	1ns
$end
$scope module priority_encoder_new_tb $end
$var wire 3 ! out [2:0] $end
$var reg 8 " d [7:0] $end
$var reg 1 # valid $end
$scope module uut $end
$var wire 8 $ d [7:0] $end
$var wire 1 # valid $end
$var reg 3 % out [2:0] $end
$var integer 32 & i [31:0] $end
$upscope $end
$upscope $end
$enddefinitions $end
$comment Show the parameter values. $end
$dumpall
$end
#0
$dumpvars
bx &
b0 %
b0 $
0#
b0 "
b0 !
$end
#3
b1000 &
b1 "
b1 $
1#
#6
b1 !
b1 %
b1000 &
b10 "
b10 $
#9
b10 !
b10 %
b1000 &
b100 "
b100 $
#12
b11 !
b11 %
b1000 &
b1000 "
b1000 $
#15
b100 !
b100 %
b1000 &
b10000 "
b10000 $
#18
b101 !
b101 %
b1000 &
b100000 "
b100000 $
#21
b110 !
b110 %
b1000 &
b1000000 "
b1000000 $
#24
b111 !
b111 %
b1000 &
b10000000 "
b10000000 $
