FSM_even_odd/FSM_evod.v
module FSM_evod (x, clk, z);

    input x;
    reg eve_odd;
    input clk;
    output reg z;
    parameter EVEN = 0, ODD = 1, S0 = 0, S1 = 1;

    always @(posedge clk) begin
        case (eve_odd)
        
            EVEN: begin
            z <= x ? 0:1;
            eve_odd <= x ? EVEN : ODD;
            end

            ODD: begin
            z <= x ? 1:0;
            eve_odd <= x ? ODD : EVEN;
            end

        default: eve_odd <= EVEN;
        endcase
    end

endmodule

FSM_even_odd/FSM_evod_tb.v
`timescale 1ps/1ps
`include "FSM_evod.v"

module FSM_evod_tb;

    reg x, clk;        
    wire z;            

    FSM_evod uut (.x(x), .clk(clk), .z(z));

    initial begin
        $dumpfile("FSM_evod.vcd"); 
        $dumpvars(0, FSM_evod_tb);

        $monitor("Time = %t || x = %b || z = %b", $time, x, z);

        clk = 1'b0;
        x = 1'b0; 

        #2  x = 0; #10 x = 1; #10 x = 1; #10 x = 1;
        #10 x = 0; #10 x = 1; #10 x = 1; #10 x = 0;
        #10 x = 0; #10 x = 1; #10 x = 1; #10 x = 0;
        #10 $finish;
    end

    always #5 clk = ~clk;

endmodule

FSM_even_odd/FSM_evod.vcd
$date
	Fri Jul 11 13:46:50 2025
$end
$version
	Icarus Verilog
$end
$timescale
	1ps
$end
$scope module FSM_evod_tb $end
$var wire 1 ! z $end
$var reg 1 " clk $end
$var reg 1 # x $end
$scope module uut $end
$var wire 1 " clk $end
$var wire 1 # x $end
$var parameter 32 $ EVEN $end
$var parameter 32 % ODD $end
$var parameter 32 & S0 $end
$var parameter 32 ' S1 $end
$var reg 1 ( eve_odd $end
$var reg 1 ! z $end
$upscope $end
$upscope $end
$enddefinitions $end
$comment Show the parameter values. $end
$dumpall
b1 '
b0 &
b1 %
b0 $
$end
#0
$dumpvars
x(
0#
0"
x!
$end
#5
0(
1"
#10
0"
#12
1#
#15
0!
1"
#20
0"
#25
1"
#30
0"
#35
1"
#40
0"
#42
0#
#45
1(
1!
1"
#50
0"
#52
1#
#55
1"
#60
0"
#65
1"
#70
0"
#72
0#
#75
0(
0!
1"
#80
0"
#85
1(
1!
1"
#90
0"
#92
1#
#95
1"
#100
0"
#105
1"
#110
0"
#112
0#
#115
0(
0!
1"
