Seven_segement_display/seven_segement.v
module seven_segement (clk, rst, bin_in, dp_en, blink_in, blink_rate, seg, dp, en);

input clk, rst,  dp_en, blink_in;
input [3:0] bin_in;
input [23:0] blink_rate;
output reg [6:0] seg ; // MSB- A, LSB- G
output reg dp;
output reg en; 

reg [23:0] blink_counter = 0;
reg blink_state = 1'b1;

always @(posedge clk or posedge rst) begin
    if (rst) begin
        seg <= 7'b1111111;
        dp <= 1'b1;
        en <= 1'b0;
    end else begin
    case (bin_in)
    4'b0000: seg <= 7'b1111110;
    4'b0001: seg <= 7'b0110000;
    4'b0010: seg <= 7'b1101101;
    4'b0011: seg <= 7'b1111001;
    4'b0100: seg <= 7'b0110011;
    4'b0101: seg <= 7'b1011011;
    4'b0110: seg <= 7'b1011111;
    4'b0111: seg <= 7'b1110000;
    4'b1000: seg <= 7'b1111111;
    4'b1001: seg <= 7'b1111011;
    endcase
    end

    if (dp_en == 1'b1) begin
        dp = 1'b0;
    end 

    if (blink_in == 1'b1) begin
        if (blink_counter >= blink_rate) begin
            blink_counter <= 0;
            blink_state <= ~blink_state;
        end else begin
            blink_counter <= blink_counter + 1;
        end
        en <= blink_state;
    end else begin
        en <= 1'b1;  // always ON if blinking is disabled
    end
end
    
endmodule

Seven_segement_display/seven_segement_tb.v
`timescale 1ns/1ns
`include "seven_segement.v"

module seven_segement_tb;

reg clk, rst,  dp_en, blink_in;
reg [3:0] bin_in;
reg [23:0] blink_rate;
wire [6:0] seg ; // MSB- A, LSB- G
wire dp;
wire en;

seven_segement uut (clk, rst, bin_in, dp_en, blink_in, blink_rate, seg, dp, en);

initial begin
    $dumpfile("seven_segement.vcd");
    $dumpvars(0, seven_segement_tb);

    $monitor("Time: %0t || clk: %0b || rst: %0b || bin_in: %04b || dp_en: %0b || blink_in: %0b || seg: %07b || dp: %0b || en: %0b", $time, clk, rst, bin_in, dp_en, blink_in, seg, dp, en);

    clk = 0;
    rst = 1;
    dp_en = 0;
    blink_in = 0;
    bin_in = 4'b0000;
    blink_rate = 24'd10;

    #8 rst = 0;
    #3 bin_in = 4'b0010;
    #10 dp_en = 1;
    #10 blink_in = 1;
    #30 bin_in = 4'b0101;
    #50 blink_rate = 24'd6;
    #50 blink_in = 0;
    dp_en = 0;
    #20 bin_in = 4'b1001;
    #50 $finish;
end

always #5 clk = ~clk;

endmodule

Seven_segement_display/seven_segement.vcd
$date
	Fri Aug 01 12:27:36 2025
$end
$version
	Icarus Verilog
$end
$timescale
	1ns
$end
$scope module seven_segement_tb $end
$var wire 7 ! seg [6:0] $end
$var wire 1 " en $end
$var wire 1 # dp $end
$var reg 4 $ bin_in [3:0] $end
$var reg 1 % blink_in $end
$var reg 24 & blink_rate [23:0] $end
$var reg 1 ' clk $end
$var reg 1 ( dp_en $end
$var reg 1 ) rst $end
$scope module uut $end
$var wire 4 * bin_in [3:0] $end
$var wire 1 % blink_in $end
$var wire 24 + blink_rate [23:0] $end
$var wire 1 ' clk $end
$var wire 1 ( dp_en $end
$var wire 1 ) rst $end
$var reg 24 , blink_counter [23:0] $end
$var reg 1 - blink_state $end
$var reg 1 # dp $end
$var reg 1 " en $end
$var reg 7 . seg [6:0] $end
$upscope $end
$upscope $end
$enddefinitions $end
$comment Show the parameter values. $end
$dumpall
$end
#0
$dumpvars
b1111110 .
1-
b0 ,
b1010 +
b0 *
1)
0(
0'
b1010 &
0%
b0 $
1#
1"
b1111110 !
$end
#5
1"
b1111110 !
b1111110 .
1'
#8
0)
#10
0'
#11
b10 $
b10 *
#15
b1101101 !
b1101101 .
1'
#20
0'
#21
1(
#25
0#
1'
#30
0'
#31
1%
#35
b1 ,
1'
#40
0'
#45
b10 ,
1'
#50
0'
#55
b11 ,
1'
#60
0'
#61
b101 $
b101 *
#65
b100 ,
b1011011 !
b1011011 .
1'
#70
0'
#75
b101 ,
1'
#80
0'
#85
b110 ,
1'
#90
0'
#95
b111 ,
1'
#100
0'
#105
b1000 ,
1'
#110
0'
#111
b110 &
b110 +
#115
0-
b0 ,
1'
#120
0'
#125
0"
b1 ,
1'
#130
0'
#135
b10 ,
1'
#140
0'
#145
b11 ,
1'
#150
0'
#155
b100 ,
1'
#160
0'
#161
0(
0%
#165
1"
1'
#170
0'
#175
1'
#180
0'
#181
b1001 $
b1001 *
#185
b1111011 !
b1111011 .
1'
