FSM_seq_detector/sequence_dct.v
// This is the code to detect '0111' sequence
 
module sequence_dct (clk, rst, in, out);

input clk, rst, in;
output reg out;

reg [2:0] state, next_state;
parameter S0 = 3'b000, S1 = 3'b001, S2 = 3'b010, S3 = 3'b011, S4 = 3'b100;

always @(posedge clk or posedge rst) begin
    if(rst) begin 
        state <= S0;
    end else begin
        state <= next_state;
    end
end

always @(*) begin
    out = 0;
    case (state)
    S0: next_state = in ? S0:S1;
    S1: next_state = in ? S2:S1;
    S2: next_state = in ? S3:S0;
    S3: next_state = in ? S4:S0;
    S4: begin
        next_state = in ? S0:S1;
        out = 1'b1;
    end 
    default: begin
                next_state = S0;
                out = 1'b0;
            end
    endcase
end
    
endmodule

FSM_seq_detector/sequence_dct_tb.v
`timescale 1ns/1ns
`include "sequence_dct.v"

module sequence_dct_tb;

reg clk, rst, in;
wire out;

sequence_dct uut (clk, rst, in, out);

initial begin
    $dumpfile("sequence_dct.vcd");
    $dumpvars();

    $monitor("Time: %0t || clk: %0b || rst: %0b || in: %0b || out: %0b", 
             $time, clk, rst, in, out);

    clk = 0;
    rst = 1;
    in = 0;
    #8 rst = 0;

    // -------- Test Vector 1: Exact 0111 --------
    #4  in = 1'b0;   // 0
    #10 in = 1'b1;   // 01
    #10 in = 1'b1;   // 011
    #10 in = 1'b1;   // 0111 --> should detect here

    // -------- Test Vector 2: Extra 1's after match (overlapping) --------
    #10 in = 1'b1;   // Another 1 — check overlap or reset

    // -------- Test Vector 3: Random noise before valid sequence --------
    #10 in = 1'b1;
    #10 in = 1'b0;   // Restart
    #10 in = 1'b1;
    #10 in = 1'b1;
    #10 in = 1'b1;   // Should detect again

    // -------- Test Vector 4: Incomplete match --------
    #10 in = 1'b0;
    #10 in = 1'b1;
    #10 in = 1'b0;   // Broken sequence, no detection

    // -------- Test Vector 5: Multiple sequences --------
    #10 in = 1'b0;
    #10 in = 1'b1;
    #10 in = 1'b1;
    #10 in = 1'b1;   // 0111 → detect
    #10 in = 1'b0;
    #10 in = 1'b1;
    #10 in = 1'b1;
    #10 in = 1'b1;   // 0111 again → detect

    #20 $finish;
end

always #5 clk = ~clk;

endmodule

FSM_seq_detector/sequence_dct.vcd
$date
	Tue Jul 22 20:26:47 2025
$end
$version
	Icarus Verilog
$end
$timescale
	1ns
$end
$scope module sequence_dct_tb $end
$var wire 1 ! out $end
$var reg 1 " clk $end
$var reg 1 # in $end
$var reg 1 $ rst $end
$scope module uut $end
$var wire 1 " clk $end
$var wire 1 # in $end
$var wire 1 $ rst $end
$var parameter 3 % S0 $end
$var parameter 3 & S1 $end
$var parameter 3 ' S2 $end
$var parameter 3 ( S3 $end
$var parameter 3 ) S4 $end
$var reg 3 * next_state [2:0] $end
$var reg 1 ! out $end
$var reg 3 + state [2:0] $end
$upscope $end
$upscope $end
$enddefinitions $end
$comment Show the parameter values. $end
$dumpall
b100 )
b11 (
b10 '
b1 &
b0 %
$end
#0
$dumpvars
b0 +
b1 *
1$
0#
0"
0!
$end
#5
1"
#8
0$
#10
0"
#15
b1 +
1"
#20
0"
#22
b10 *
1#
#25
b11 *
b10 +
1"
#30
0"
#35
b100 *
b11 +
1"
#40
0"
#45
1!
b0 *
b100 +
1"
#50
0"
#55
0!
b0 +
1"
#60
0"
#65
1"
#70
0"
#72
b1 *
0#
#75
b1 +
1"
#80
0"
#82
b10 *
1#
#85
b11 *
b10 +
1"
#90
0"
#95
b100 *
b11 +
1"
#100
0"
#105
1!
b0 *
b100 +
1"
#110
0"
#112
b1 *
1!
0#
#115
0!
b1 +
1"
#120
0"
#122
b10 *
1#
#125
b11 *
b10 +
1"
#130
0"
#132
b0 *
0#
#135
b1 *
b0 +
1"
#140
0"
#145
b1 +
1"
#150
0"
#152
b10 *
1#
#155
b11 *
b10 +
1"
#160
0"
#165
b100 *
b11 +
1"
#170
0"
#175
1!
b0 *
b100 +
1"
#180
0"
#182
b1 *
1!
0#
#185
0!
b1 +
1"
#190
0"
#192
b10 *
1#
#195
b11 *
b10 +
1"
#200
0"
#205
b100 *
b11 +
1"
#210
0"
#215
1!
b0 *
b100 +
1"
#220
0"
#225
0!
b0 +
1"
