Decoder (3 to 8)/decoder.v
module decoder (out, sel, enable);

input enable;
input [2:0] sel;
output reg [7:0] out;

always @(*) begin
    if (!enable)
        out = 8'b00000000;  
    else begin
        case (sel)
            3'b000: out = 8'b00000001;
            3'b001: out = 8'b00000010;
            3'b010: out = 8'b00000100;
            3'b011: out = 8'b00001000;
            3'b100: out = 8'b00010000;
            3'b101: out = 8'b00100000;
            3'b110: out = 8'b01000000;
            3'b111: out = 8'b10000000;
            default: out = 8'b00000000;  
        endcase
    end
end

endmodule

Decoder (3 to 8)/decoder_tb.v
`timescale 1ns/1ns
`include "decoder.v"

module decoder_tb;

    reg [2:0] sel;
    reg enable;
    wire [7:0] out;

    decoder uut (.sel(sel), .enable(enable), .out(out));

    initial begin
        
        $monitor("Time = %0t || sel = %b || enable = %b || out = %b", $time, sel, enable, out);

        enable = 1;

        #5 sel = 3'b000;
        #5 sel = 3'b001;
        #5 sel = 3'b010;
        #5 sel = 3'b011;
        #5 sel = 3'b100;
        #5 sel = 3'b101;
        #5 sel = 3'b110;
        #5 sel = 3'b111;

        #5 $display("The program is successfully completed");
        #5 $finish;
    end

    initial begin
        $dumpfile("decoder_tb.vcd");
        $dumpvars(0, decoder_tb);
    end

endmodule

Decoder (3 to 8)/decoder_tb.vcd
$date
	Sat Jun 28 18:31:51 2025
$end
$version
	Icarus Verilog
$end
$timescale
	1ns
$end
$scope module decoder_tb $end
$var wire 8 ! out [7:0] $end
$var reg 1 " enable $end
$var reg 3 # sel [2:0] $end
$scope module uut $end
$var wire 1 " enable $end
$var wire 3 $ sel [2:0] $end
$var reg 8 % out [7:0] $end
$upscope $end
$upscope $end
$enddefinitions $end
$comment Show the parameter values. $end
$dumpall
$end
#0
$dumpvars
b0 %
bx $
bx #
1"
b0 !
$end
#5
b1 !
b1 %
b0 #
b0 $
#10
b10 !
b10 %
b1 #
b1 $
#15
b100 !
b100 %
b10 #
b10 $
#20
b1000 !
b1000 %
b11 #
b11 $
#25
b10000 !
b10000 %
b100 #
b100 $
#30
b100000 !
b100000 %
b101 #
b101 $
#35
b1000000 !
b1000000 %
b110 #
b110 $
#40
b10000000 !
b10000000 %
b111 #
b111 $
