Johnson_ring_counter/johnson_counter.v
module johnson_counter (clk, rst, q);

input clk;
input rst;
output reg [3:0] q;

always @(posedge clk or posedge rst) begin
    if (rst)
        q <= 4'b0000;
    else begin
        q <= {q[2:0], ~q[3]};
    end
end

endmodule

Johnson_ring_counter/johnson_counter_tb.v
`timescale 1ns/1ns
`include "johnson_counter.v"

module johnson_counter_tb;

    reg clk = 0, rst = 1;
    wire [3:0] q;

    johnson_counter uut (.clk(clk), .rst(rst), .q(q));

    always #5 clk = ~clk;

    initial begin
        $dumpfile("johnson_counter.vcd");
        $dumpvars(0, johnson_counter_tb);

        #10 rst = 0;
        #85 $finish;
    end

    initial begin
        $monitor("Time: %0t | q: %b", $time, q);
    end
endmodule

Johnson_ring_counter/johnson_counter.vcd
$date
	Mon Jul 07 21:13:12 2025
$end
$version
	Icarus Verilog
$end
$timescale
	1ns
$end
$scope module johnson_counter_tb $end
$var wire 4 ! q [3:0] $end
$var reg 1 " clk $end
$var reg 1 # rst $end
$scope module uut $end
$var wire 1 " clk $end
$var wire 1 # rst $end
$var reg 4 $ q [3:0] $end
$upscope $end
$upscope $end
$enddefinitions $end
$comment Show the parameter values. $end
$dumpall
$end
#0
$dumpvars
b0 $
1#
0"
b0 !
$end
#5
1"
#10
0"
0#
#15
b1 !
b1 $
1"
#20
0"
#25
b11 !
b11 $
1"
#30
0"
#35
b111 !
b111 $
1"
#40
0"
#45
b1111 !
b1111 $
1"
#50
0"
#55
b1110 !
b1110 $
1"
#60
0"
#65
b1100 !
b1100 $
1"
#70
0"
#75
b1000 !
b1000 $
1"
#80
0"
#85
b0 !
b0 $
1"
#90
0"
#95
b1 !
b1 $
1"
