3_input_majority_gate/majority_gate.v
module majority_gate (a, b, c, out);

input a, b, c;
output out;

//This is basically like VOTING MACHINE, The output will be 1 if there are majority 1's in the input and 0 if there are majority 0's in the input

assign out = (c & (a^b)) | (a&b);

endmodule

3_input_majority_gate/majority_gate_tb.v
`timescale 1ns/1ns
`include "majority_gate.v"
module majority_gate_tb;

reg a, b, c;
wire out;
integer i;

majority_gate uut (a, b, c, out);

initial begin
  $dumpfile("majority_gate.vcd");
  $dumpvars(0, majority_gate_tb);

  $monitor("a: %0b || b: %0b || c: %0b || out: %0b", a, b, c, out);

  for (i = 0; i < 8; i = i + 1) begin
    {a,b,c} = i;
    #10;
  end
end
    
endmodule

3_input_majority_gate/majority_gate.vcd
$date
	Tue Aug 12 10:49:02 2025
$end
$version
	Icarus Verilog
$end
$timescale
	1ns
$end
$scope module majority_gate_tb $end
$var wire 1 ! out $end
$var reg 1 " a $end
$var reg 1 # b $end
$var reg 1 $ c $end
$var integer 32 % i [31:0] $end
$scope module uut $end
$var wire 1 " a $end
$var wire 1 # b $end
$var wire 1 $ c $end
$var wire 1 ! out $end
$upscope $end
$upscope $end
$enddefinitions $end
$comment Show the parameter values. $end
$dumpall
$end
#0
$dumpvars
b0 %
0$
0#
0"
0!
$end
#10
1$
b1 %
#20
1#
0$
b10 %
#30
1!
1$
b11 %
#40
0!
1"
0#
0$
b100 %
#50
1!
1$
b101 %
#60
1#
0$
b110 %
#70
1$
b111 %
#80
b1000 %
