BCD_10_counter/bcd_counter.v
module bcd_counter (clk, rst, out);

input clk, rst;
output reg [3:0] out; 

always @(posedge clk or posedge rst) begin
    if(rst) out <= 4'b0000;
    else if (out == 4'b1001) out <= 4'b0000;
    else out <= out + 1;
end
endmodule

BCD_10_counter/bcd_counter_tb.v
`timescale 1ns/1ns 
`include "bcd_counter.v"

module bcd_counter_tb;

wire [3:0] out;
reg clk, rst;

bcd_counter uut (.clk(clk), .rst(rst), .out(out));

initial begin
    $dumpfile("bcd_counter.vcd");
    $dumpvars(0, bcd_counter_tb);

    clk = 0;
    rst = 1'b1; 
    

    $monitor("Time: %0t || clk: %0b || rst: %0b || count: %04b", $time, clk, rst, out); 

    #8 rst = 0;
    
    #100 $finish;
end
    
always #5 clk = ~clk;

endmodule

BCD_10_counter/bcd_counter.vcd
$date
	Tue Jul 08 20:13:26 2025
$end
$version
	Icarus Verilog
$end
$timescale
	1ns
$end
$scope module bcd_counter_tb $end
$var wire 4 ! out [3:0] $end
$var reg 1 " clk $end
$var reg 1 # rst $end
$scope module uut $end
$var wire 1 " clk $end
$var wire 1 # rst $end
$var reg 4 $ out [3:0] $end
$upscope $end
$upscope $end
$enddefinitions $end
$comment Show the parameter values. $end
$dumpall
$end
#0
$dumpvars
b0 $
1#
0"
b0 !
$end
#5
1"
#8
0#
#10
0"
#15
b1 !
b1 $
1"
#20
0"
#25
b10 !
b10 $
1"
#30
0"
#35
b11 !
b11 $
1"
#40
0"
#45
b100 !
b100 $
1"
#50
0"
#55
b101 !
b101 $
1"
#60
0"
#65
b110 !
b110 $
1"
#70
0"
#75
b111 !
b111 $
1"
#80
0"
#85
b1000 !
b1000 $
1"
#90
0"
#95
b1001 !
b1001 $
1"
#100
0"
#105
b0 !
b0 $
1"
