Universal_shift_register/shift_register.v
module shift_register (clk, rst, sel, d, q);
    
input clk;
input rst;
input [1:0] sel;    
input [3:0] d;
output reg [3:0] q;

// 00 - Hold, 01 - Shift Right, 10 - Shift Left, 11 - Parallel Load
always @(posedge clk or posedge rst) begin
    if (rst)
        q <= 4'b0000;
    else begin
        case (sel)
            2'b00: q <= q;          
            2'b01: q <= q >> 1;     
            2'b10: q <= q << 1;     
            2'b11: q <= d;  // Parallel Load
        endcase
    end
end

endmodule

Universal_shift_register/shift_register_tb.v
`timescale 1ns/1ns
`include "shift_register.v"

module shift_register_tb;

reg clk, rst;
reg [1:0] sel;
reg [3:0] d;
wire [3:0] q;
    
shift_register uut (.clk(clk), .rst(rst), .sel(sel), .d(d), .q(q));

always #5 clk = ~clk;

initial begin

    $dumpfile("shift_register.vcd");
    $dumpvars(0, shift_register_tb);

    $monitor("time: %0t || sel: %02b || d: %04b || q: %04b", $time, sel, d, q);

    clk = 0; 
    rst = 1; sel = 2'b00; d = 4'b0000;
    #10 rst = 0;

    #10 sel = 2'b11; d = 4'b1010;
    #10 sel = 2'b00;
    #10 sel = 2'b01;
    #10 sel = 2'b10;
    #10 sel = 2'b11; d = 4'b1100;
    #10 sel = 2'b01;
    #10 sel = 2'b01;
    #10 sel = 2'b10;
    #10 sel = 2'b10;

    #20 $finish;
end

endmodule

Universal_shift_register/shift_register.vcd
$date
	Wed Jul 09 21:39:02 2025
$end
$version
	Icarus Verilog
$end
$timescale
	1ns
$end
$scope module shift_register_tb $end
$var wire 4 ! q [3:0] $end
$var reg 1 " clk $end
$var reg 4 # d [3:0] $end
$var reg 1 $ rst $end
$var reg 2 % sel [1:0] $end
$scope module uut $end
$var wire 1 " clk $end
$var wire 4 & d [3:0] $end
$var wire 1 $ rst $end
$var wire 2 ' sel [1:0] $end
$var reg 4 ( q [3:0] $end
$upscope $end
$upscope $end
$enddefinitions $end
$comment Show the parameter values. $end
$dumpall
$end
#0
$dumpvars
b0 (
b0 '
b0 &
b0 %
1$
b0 #
0"
b0 !
$end
#5
1"
#10
0"
0$
#15
1"
#20
0"
b1010 #
b1010 &
b11 %
b11 '
#25
b1010 !
b1010 (
1"
#30
0"
b0 %
b0 '
#35
1"
#40
0"
b1 %
b1 '
#45
b101 !
b101 (
1"
#50
0"
b10 %
b10 '
#55
b1010 !
b1010 (
1"
#60
0"
b1100 #
b1100 &
b11 %
b11 '
#65
b1100 !
b1100 (
1"
#70
0"
b1 %
b1 '
#75
b110 !
b110 (
1"
#80
0"
#85
b11 !
b11 (
1"
#90
0"
b10 %
b10 '
#95
b110 !
b110 (
1"
#100
0"
#105
b1100 !
b1100 (
1"
#110
0"
#115
b1000 !
b1000 (
1"
