101_detector/seq_detect.v
// This is the code to detect '101' sequence
 
module seq_detect (clk, rst, in, out);

input clk, rst, in;
output reg out;

reg [1:0] state, next_state;
parameter S0 = 2'b00, S1 = 2'b01, S2 = 2'b10, S3 = 2'b11;

always @(posedge clk or posedge rst) begin
    if(rst) begin 
        state <= S0;
    end else begin
        state <= next_state;
    end
end

always @(*) begin
    out = 0;
    case (state)
    S0: next_state = in ? S1:S0;
    S1: next_state = in ? S1:S2;
    S2: next_state = in ? S3:S0;
    S3: begin
        next_state = in ? S1:S2;
        out = 1'b1;
    end 
    default: begin
                next_state = S0;
                out = 1'b0;
            end
    endcase
end
    
endmodule

101_detector/seq_detect_tb.v
`timescale 1ns/1ns
`include "seq_detect.v"

module seq_detect_tb;

reg clk, rst, in;
wire out;

seq_detect uut (clk, rst, in, out);

initial begin
    $dumpfile("seq_detect.vcd");
    $dumpvars(0, seq_detect_tb);

    $monitor("Time: %0t || clk: %0b || rst: %0b || in: %0b || out: %0b", $time, clk, rst, in, out);

    clk = 0;
    rst = 1;
    in = 0;
    #8 rst = 0;

    #4  in = 1'b1;
    #10 in = 1'b0;
    #10 in = 1'b1;

    #10 in = 1'b0;
    #10 in = 1'b0;
    #10 in = 1'b0;

    #10 in = 1'b1;
    #10 in = 1'b1;
    #10 in = 1'b0;
    #10 in = 1'b1;

    #10 in = 1'b1;
    #10 in = 1'b1;
    #10 in = 1'b1;
    #10 in = 1'b1;

    #10 in = 1'b1;
    #10 in = 1'b0;
    #10 in = 1'b1;
    #10 in = 1'b1;
    #10 in = 1'b0;
    #10 in = 1'b1;

    #10 $finish;
end

always #5 clk = ~clk;

endmodule

101_detector/seq_detect.vcd
$date
	Tue Jul 22 17:44:41 2025
$end
$version
	Icarus Verilog
$end
$timescale
	1ns
$end
$scope module seq_detect_tb $end
$var wire 1 ! out $end
$var reg 1 " clk $end
$var reg 1 # in $end
$var reg 1 $ rst $end
$scope module uut $end
$var wire 1 " clk $end
$var wire 1 # in $end
$var wire 1 $ rst $end
$var parameter 2 % S0 $end
$var parameter 2 & S1 $end
$var parameter 2 ' S2 $end
$var parameter 2 ( S3 $end
$var reg 2 ) next_state [1:0] $end
$var reg 1 ! out $end
$var reg 2 * state [1:0] $end
$upscope $end
$upscope $end
$enddefinitions $end
$comment Show the parameter values. $end
$dumpall
b11 (
b10 '
b1 &
b0 %
$end
#0
$dumpvars
b0 *
b0 )
1$
0#
0"
0!
$end
#5
1"
#8
0$
#10
0"
#12
b1 )
1#
#15
b1 *
1"
#20
0"
#22
b10 )
0#
#25
b0 )
b10 *
1"
#30
0"
#32
b11 )
1#
#35
1!
b1 )
b11 *
1"
#40
0"
#42
b10 )
1!
0#
#45
b0 )
0!
b10 *
1"
#50
0"
#55
b0 *
1"
#60
0"
#65
1"
#70
0"
#72
b1 )
1#
#75
b1 *
1"
#80
0"
#85
1"
#90
0"
#92
b10 )
0#
#95
b0 )
b10 *
1"
#100
0"
#102
b11 )
1#
#105
1!
b1 )
b11 *
1"
#110
0"
#115
0!
b1 *
1"
#120
0"
#125
1"
#130
0"
#135
1"
#140
0"
#145
1"
#150
0"
#155
1"
#160
0"
#162
b10 )
0#
#165
b0 )
b10 *
1"
#170
0"
#172
b11 )
1#
#175
1!
b1 )
b11 *
1"
#180
0"
#185
0!
b1 *
1"
#190
0"
#192
b10 )
0#
#195
b0 )
b10 *
1"
#200
0"
#202
b11 )
1#
#205
1!
b1 )
b11 *
1"
